climan/__init__.py
climan/configs.py
climan/managers.py
climan-0.3.1.dist-info/licenses/LICENSE
climan-0.3.1.dist-info/METADATA
climan-0.3.1.dist-info/WHEEL
climan-0.3.1.dist-info/top_level.txt
climan-0.3.1.dist-info/RECORD
