Metadata-Version: 2.4
Name: climan
Version: 0.3.1
Summary: Cross-platform config and manager for click console utilities.
Home-page: https://github.com/smartlegionlab/climan/
Author: A.A. Suvorov
Author-email: smartlegiondev@gmail.com
License: BSD 3-Clause License
Project-URL: Documentation, https://github.com/smartlegionlab/climan/blob/master/README.md
Project-URL: Release notes, https://github.com/smartlegionlab/climan/releases
Keywords: climan,click,click manager
Classifier: Development Status :: 5 - Production/Stable
Classifier: License :: OSI Approved :: BSD License
Classifier: Natural Language :: English
Classifier: Operating System :: OS Independent
Classifier: Operating System :: Microsoft :: Windows
Classifier: Operating System :: POSIX :: Linux
Classifier: Programming Language :: Python :: 3 :: Only
Classifier: Topic :: Software Development :: Libraries :: Python Modules
Requires-Python: >=3.6
License-File: LICENSE
Requires-Dist: click~=8.0.1
Dynamic: license-file
